satbucket/__init__.py
satbucket/_version.py
satbucket/analysis.py
satbucket/checks.py
satbucket/dataframe.py
satbucket/filters.py
satbucket/info.py
satbucket/io.py
satbucket/partitioning.py
satbucket/readers.py
satbucket/routines.py
satbucket/writers.py
satbucket/utils/dask.py
satbucket/utils/directories.py
satbucket/utils/parallel.py
satbucket/utils/time.py
satbucket/utils/timing.py
satbucket/utils/yaml.py
satellite_bucket-0.0.3.dist-info/licenses/LICENSE
satellite_bucket-0.0.3.dist-info/METADATA
satellite_bucket-0.0.3.dist-info/WHEEL
satellite_bucket-0.0.3.dist-info/top_level.txt
satellite_bucket-0.0.3.dist-info/RECORD
